Workbook

Sheet Parâmetros
A1: Parâmetro | B1: Valor | C1: Unidade | D1: Fonte / fórmula
A2: Custo médio anual por aluno de universidade federal (2023) | B2: 52533 | C2: R$/ano | D2: MEC, ano-base 2023 (Poder360, 2025)
A3: Fator do IPCA acumulado de jan/2024 a set/2026 | B3: 1.136206 | C3: fator | D3: Série 433 do Banco Central, consulta em 25/10/2026
A4: Custo anual por aluno corrigido para 2026 | B4: =$B$2*$B$3 -> 59688.31 | C4: R$/ano | D4: custo de 2023 × fator do IPCA
A5: Créditos cursados por ano | B5: 46.4 | C5: créditos | D5: 232 créditos do fluxo de Engenharia de Software em 10 semestres
A6: Custo por crédito | B6: =$B$4/$B$5 -> 1286.386 | C6: R$ | D6: custo anual corrigido ÷ créditos por ano
A7: Créditos da disciplina (FGA0206) | B7: 4 | C7: créditos | D7: 2 teóricos e 2 práticos, 60 h; 2 deles de extensão
A8: Custo da disciplina por estudante | B8: =$B$6*$B$7 -> 5145.5439 | C8: R$ | D8: custo por crédito × créditos
A9: Semanas do semestre | B9: 18 | C9: semanas | D9: Cronograma da disciplina (10/08 a 14/12/2026)
A10: Custo semanal da disciplina por estudante | B10: =$B$8/$B$9 -> 285.86355 | C10: R$/semana | D10: custo da disciplina ÷ semanas
A11: Carga semanal por integrante | B11: 12 | C11: h/semana | D11: 4,5 h de cerimônias e 7,5 h assíncronas; time 100% remoto
A12: Parcela síncrona da carga semanal | B12: 4.5 | C12: h/semana | D12: Planning 1 h, review 1 h, retrospectiva 1 h e reunião com POs 1,5 h
A13: Tarifa de energia | B13: 0.83429 | C13: R$/kWh | D13: Neoenergia Brasília, REH 3.614, vigência 22/10/2026
A14: Consumo em hora de trabalho | B14: 0.075 | C14: kWh/h | D14: Notebook em carga de desenvolvimento (~65 W) e roteador (~10 W)
A15: Energia por integrante | B15: =$B$11*$B$14*$B$13 -> 0.750861 | C15: R$/semana | D15: horas de trabalho × consumo × tarifa
A16: Plano de internet residencial | B16: 99.9 | C16: R$/mês | D16: Oi fibra (DF)
A17: Horas por mês para rateio da internet | B17: 730 | C17: h/mês | D17: Mês médio real (8.766 h por ano ÷ 12)
A18: Internet por integrante (rateio pelas horas de projeto) | B18: =$B$16/$B$17*$B$11 -> 1.6421918 | C18: R$/semana | D18: (plano ÷ horas do mês) × horas de trabalho
A19: Valor de referência do notebook | B19: 4047.99 | C19: R$ | D19: Equipamento padrão adotado pela equipe
A20: Valor residual do equipamento | B20: 0.1 | C20: fração | D20: Regra do setor público (STN, macrofunção 020330)
A21: Vida útil do equipamento | B21: 260 | C21: semanas | D21: 60 meses (STN, macrofunção 020330)
A22: Depreciação por integrante | B22: =$B$19*(1-$B$20)/$B$21 -> 14.012273 | C22: R$/semana | D22: valor depreciável (90%) ÷ semanas de vida útil
A23: Cotação do dólar | B23: 4.9652 | C23: R$/US$ | D23: AwesomeAPI, 23/10/2026
A24: Plano Railway Hobby | B24: 5 | C24: US$/mês | D24: Railway, Pricing Plans
A25: Semanas por mês | B25: 4.33 | C25: semanas | D25: Média (52 ÷ 12)
A26: Hospedagem do projeto (Railway) | B26: =$B$24*$B$23/$B$25 -> 5.7334873 | C26: R$/semana | D26: plano × cotação ÷ semanas por mês
A27: Custo semanal por integrante | B27: =$B$10+$B$15+$B$18+$B$22 -> 302.26888 | C27: R$/semana | D27: disciplina + energia + internet + depreciação
A28: Custo-hora do estudante da UnB | B28: =$B$27/$B$11 -> 25.189073 | C28: R$/h | D28: custo semanal por integrante ÷ carga semanal
A29: Horas por story point | B29: 8 | C29: h/SP | D29: Referência da disciplina para desenvolvedor júnior
A30: Custo por story point | B30: =$B$28*$B$29 -> 201.51259 | C30: R$/SP | D30: custo-hora × horas por SP
A31: Equipe baseline (plano do início do semestre) | B31: 13 | C31: pessoas | D31: Levantamento de disponibilidade da primeira semana; base do PV/BAC
A32: Equipe efetiva atual | B32: 11 | C32: pessoas | D32: Integrantes listados na documentação; base do AC
A33: Custo semanal do projeto (baseline) | B33: =$B$27*$B$31+$B$26 -> 3935.2289 | C33: R$/semana | D33: custo por integrante × equipe baseline + hospedagem
A34: Custo semanal do projeto (equipe efetiva) | B34: =$B$27*$B$32+$B$26 -> 3330.6912 | C34: R$/semana | D34: custo por integrante × equipe efetiva + hospedagem
A35: Semanas dentro das releases | B35: 15 | C35: semanas | D35: R1 6 + R2 4 + R3 5
A36: BAC do projeto (15 semanas de release) | B36: =$B$33*$B$35 -> 59028.434 | C36: R$ | D36: custo semanal baseline × semanas de release

Sheet Custo por integrante
A1: Componente | B1: R$/semana | C1: Como é calculado
A2: Disciplina (custo do estudante para a UnB) | B2: =Parâmetros!$B$10 -> 285.86355 | C2: Custo da disciplina por estudante ÷ 18 semanas
A3: Depreciação do notebook | B3: =Parâmetros!$B$22 -> 14.012273 | C3: Valor depreciável (90% de R$ 4.047,99) ÷ 260 semanas
A4: Internet (rateio pelas horas de projeto) | B4: =Parâmetros!$B$18 -> 1.6421918 | C4: (Plano ÷ 730 h do mês) × 12 h por semana
A5: Energia | B5: =Parâmetros!$B$15 -> 0.750861 | C5: 12 h × 0,075 kWh/h × tarifa da Neoenergia
A6: Total por integrante | B6: =Parâmetros!$B$27 -> 302.26888 | C6: soma dos componentes
A7: Custo-hora | B7: =Parâmetros!$B$28 -> 25.189073 | C7: total por integrante ÷ 12 h por semana
A8: Custo por story point | B8: =Parâmetros!$B$30 -> 201.51259 | C8: custo-hora × 8 h por SP
A9: Hospedagem (Railway, custo do projeto) | B9: =Parâmetros!$B$26 -> 5.7334873 | C9: US$ 5,00/mês convertidos e rateados por semana
A10: Custo semanal do projeto (baseline, 13) | B10: =Parâmetros!$B$33 -> 3935.2289 | C10: total por integrante × 13 + hospedagem
A11: Custo semanal do projeto (equipe efetiva, 11) | B11: =Parâmetros!$B$34 -> 3330.6912 | C11: total por integrante × 11 + hospedagem

Sheet Orçamento
A1: Release | B1: Período | C1: Semanas | D1: Horas planejadas (baseline) | E1: BAC (R$)
A2: R1 | B2: 17/08 a 27/09/2026 | C2: 6 | D2: =C2*Parâmetros!$B$31*Parâmetros!$B$11 -> 936 | E2: =C2*Parâmetros!$B$33 -> 23611.373
A3: R2 | B3: 28/09 a 25/10/2026 | C3: 4 | D3: =C3*Parâmetros!$B$31*Parâmetros!$B$11 -> 624 | E3: =C3*Parâmetros!$B$33 -> 15740.916
A4: R3 | B4: 26/10 a 29/11/2026 | C4: 5 | D4: =C4*Parâmetros!$B$31*Parâmetros!$B$11 -> 780 | E4: =C4*Parâmetros!$B$33 -> 19676.145
A5: Subtotal das releases | C5: =SUM(C2:C4) -> 15 | D5: =SUM(D2:D4) -> 2340 | E5: =SUM(E2:E4) -> 59028.434
A6: Semanas fora das releases (preparação e encerramento) | B6: 10/08 a 16/08 e 30/11 a 14/12 | C6: =Parâmetros!$B$9-C5 -> 3 | D6: =C6*Parâmetros!$B$31*Parâmetros!$B$11 -> 468 | E6: =C6*Parâmetros!$B$33 -> 11805.687
A7: Total do semestre | C7: =C5+C6 -> 18 | D7: =D5+D6 -> 2808 | E7: =E5+E6 -> 70834.12
A9: O BAC de cada release é o custo semanal do projeto, com a baseline de 13 integrantes, multiplicado pelas semanas da release. As datas seguem o roadmap.

Sheet Horas
A1: Integrante | B1: Sprint | C1: Horas registradas
A2: Arthur Fonseca Vale | B2: S1
A3: Brenno da Silva Oliveira | B3: S1
A4: Caio Falcao Habibe Costa | B4: S1
A5: Carlos Eduardo de Sousa Paz | B5: S1
A6: Gabriel Freitas Balbino | B6: S1
A7: Henrique Carvalho Neves | B7: S1
A8: Joao Lucas Araujo Siqueira | B8: S1
A9: Joao Paulo Lima da Silva | B9: S1
A10: Leonardo Sobrinho De Aguiar | B10: S1
A11: Letícia Torres Soares Martins | B11: S1
A12: Rafael Melo Matuda | B12: S1
A13: Arthur Fonseca Vale | B13: S2
... A166: Rafael Melo Matuda | B166: S15

Sheet AgileEVM
A1: Release | B1: Sprint | C1: Pontos planejados | D1: Pontos concluídos | E1: PV (SP) acum. | F1: EV (SP) acum. | G1: Horas reais | H1: Horas acum. | I1: SPI | J1: PV (R$) | K1: EV (R$) | L1: AC (R$) | M1: CPI | N1: SV (R$) | O1: CV (R$) | P1: EAC (R$) | Q1: VAC (R$)
A2: R1 | B2: S1 | E2: =C2 -> 0 | F2: =D2 -> 0 | G2: =SUMIFS(Horas!$C:$C,Horas!$B:$B,$B2) -> 0 | H2: =G2 -> 0 | I2: =IFERROR(F2/E2,"") | J2: =Parâmetros!$B$33*1 -> 3935.2289 | K2: =IFERROR(I2*J2,"") | L2: =IFERROR(IF(H2=0,"",H2*Parâmetros!$B$28),"") | M2: =IFERROR(K2/L2,"") | N2: =IFERROR(K2-J2,"") | O2: =IFERROR(K2-L2,"") | P2: =IFERROR(Parâmetros!$B$36/M2,"") | Q2: =IFERROR(Parâmetros!$B$36-P2,"")
A3: R1 | B3: S2 | E3: =E2+C3 -> 0 | F3: =F2+D3 -> 0 | G3: =SUMIFS(Horas!$C:$C,Horas!$B:$B,$B3) -> 0 | H3: =H2+G3 -> 0 | I3: =IFERROR(F3/E3,"") | J3: =Parâmetros!$B$33*2 -> 7870.4578 | K3: =IFERROR(I3*J3,"") | L3: =IFERROR(IF(H3=0,"",H3*Parâmetros!$B$28),"") | M3: =IFERROR(K3/L3,"") | N3: =IFERROR(K3-J3,"") | O3: =IFERROR(K3-L3,"") | P3: =IFERROR(Parâmetros!$B$36/M3,"") | Q3: =IFERROR(Parâmetros!$B$36-P3,"")
A4: R1 | B4: S3 | E4: =E3+C4 -> 0 | F4: =F3+D4 -> 0 | G4: =SUMIFS(Horas!$C:$C,Horas!$B:$B,$B4) -> 0 | H4: =H3+G4 -> 0 | I4: =IFERROR(F4/E4,"") | J4: =Parâmetros!$B$33*3 -> 11805.687 | K4: =IFERROR(I4*J4,"") | L4: =IFERROR(IF(H4=0,"",H4*Parâmetros!$B$28),"") | M4: =IFERROR(K4/L4,"") | N4: =IFERROR(K4-J4,"") | O4: =IFERROR(K4-L4,"") | P4: =IFERROR(Parâmetros!$B$36/M4,"") | Q4: =IFERROR(Parâmetros!$B$36-P4,"")
A5: R1 | B5: S4 | E5: =E4+C5 -> 0 | F5: =F4+D5 -> 0 | G5: =SUMIFS(Horas!$C:$C,Horas!$B:$B,$B5) -> 0 | H5: =H4+G5 -> 0 | I5: =IFERROR(F5/E5,"") | J5: =Parâmetros!$B$33*4 -> 15740.916 | K5: =IFERROR(I5*J5,"") | L5: =IFERROR(IF(H5=0,"",H5*Parâmetros!$B$28),"") | M5: =IFERROR(K5/L5,"") | N5: =IFERROR(K5-J5,"") | O5: =IFERROR(K5-L5,"") | P5: =IFERROR(Parâmetros!$B$36/M5,"") | Q5: =IFERROR(Parâmetros!$B$36-P5,"")
A6: R1 | B6: S5 | E6: =E5+C6 -> 0 | F6: =F5+D6 -> 0 | G6: =SUMIFS(Horas!$C:$C,Horas!$B:$B,$B6) -> 0 | H6: =H5+G6 -> 0 | I6: =IFERROR(F6/E6,"") | J6: =Parâmetros!$B$33*5 -> 19676.145 | K6: =IFERROR(I6*J6,"") | L6: =IFERROR(IF(H6=0,"",H6*Parâmetros!$B$28),"") | M6: =IFERROR(K6/L6,"") | N6: =IFERROR(K6-J6,"") | O6: =IFERROR(K6-L6,"") | P6: =IFERROR(Parâmetros!$B$36/M6,"") | Q6: =IFERROR(Parâmetros!$B$36-P6,"")
A7: R1 | B7: S6 | E7: =E6+C7 -> 0 | F7: =F6+D7 -> 0 | G7: =SUMIFS(Horas!$C:$C,Horas!$B:$B,$B7) -> 0 | H7: =H6+G7 -> 0 | I7: =IFERROR(F7/E7,"") | J7: =Parâmetros!$B$33*6 -> 23611.373 | K7: =IFERROR(I7*J7,"") | L7: =IFERROR(IF(H7=0,"",H7*Parâmetros!$B$28),"") | M7: =IFERROR(K7/L7,"") | N7: =IFERROR(K7-J7,"") | O7: =IFERROR(K7-L7,"") | P7: =IFERROR(Parâmetros!$B$36/M7,"") | Q7: =IFERROR(Parâmetros!$B$36-P7,"")
A8: R2 | B8: S7 | E8: =E7+C8 -> 0 | F8: =F7+D8 -> 0 | G8: =SUMIFS(Horas!$C:$C,Horas!$B:$B,$B8) -> 0 | H8: =H7+G8 -> 0 | I8: =IFERROR(F8/E8,"") | J8: =Parâmetros!$B$33*7 -> 27546.602 | K8: =IFERROR(I8*J8,"") | L8: =IFERROR(IF(H8=0,"",H8*Parâmetros!$B$28),"") | M8: =IFERROR(K8/L8,"") | N8: =IFERROR(K8-J8,"") | O8: =IFERROR(K8-L8,"") | P8: =IFERROR(Parâmetros!$B$36/M8,"") | Q8: =IFERROR(Parâmetros!$B$36-P8,"")
A9: R2 | B9: S8 | E9: =E8+C9 -> 0 | F9: =F8+D9 -> 0 | G9: =SUMIFS(Horas!$C:$C,Horas!$B:$B,$B9) -> 0 | H9: =H8+G9 -> 0 | I9: =IFERROR(F9/E9,"") | J9: =Parâmetros!$B$33*8 -> 31481.831 | K9: =IFERROR(I9*J9,"") | L9: =IFERROR(IF(H9=0,"",H9*Parâmetros!$B$28),"") | M9: =IFERROR(K9/L9,"") | N9: =IFERROR(K9-J9,"") | O9: =IFERROR(K9-L9,"") | P9: =IFERROR(Parâmetros!$B$36/M9,"") | Q9: =IFERROR(Parâmetros!$B$36-P9,"")
A10: R2 | B10: S9 | E10: =E9+C10 -> 0 | F10: =F9+D10 -> 0 | G10: =SUMIFS(Horas!$C:$C,Horas!$B:$B,$B10) -> 0 | H10: =H9+G10 -> 0 | I10: =IFERROR(F10/E10,"") | J10: =Parâmetros!$B$33*9 -> 35417.06 | K10: =IFERROR(I10*J10,"") | L10: =IFERROR(IF(H10=0,"",H10*Parâmetros!$B$28),"") | M10: =IFERROR(K10/L10,"") | N10: =IFERROR(K10-J10,"") | O10: =IFERROR(K10-L10,"") | P10: =IFERROR(Parâmetros!$B$36/M10,"") | Q10: =IFERROR(Parâmetros!$B$36-P10,"")
A11: R2 | B11: S10 | E11: =E10+C11 -> 0 | F11: =F10+D11 -> 0 | G11: =SUMIFS(Horas!$C:$C,Horas!$B:$B,$B11) -> 0 | H11: =H10+G11 -> 0 | I11: =IFERROR(F11/E11,"") | J11: =Parâmetros!$B$33*10 -> 39352.289 | K11: =IFERROR(I11*J11,"") | L11: =IFERROR(IF(H11=0,"",H11*Parâmetros!$B$28),"") | M11: =IFERROR(K11/L11,"") | N11: =IFERROR(K11-J11,"") | O11: =IFERROR(K11-L11,"") | P11: =IFERROR(Parâmetros!$B$36/M11,"") | Q11: =IFERROR(Parâmetros!$B$36-P11,"")
A12: R3 | B12: S11 | E12: =E11+C12 -> 0 | F12: =F11+D12 -> 0 | G12: =SUMIFS(Horas!$C:$C,Horas!$B:$B,$B12) -> 0 | H12: =H11+G12 -> 0 | I12: =IFERROR(F12/E12,"") | J12: =Parâmetros!$B$33*11 -> 43287.518 | K12: =IFERROR(I12*J12,"") | L12: =IFERROR(IF(H12=0,"",H12*Parâmetros!$B$28),"") | M12: =IFERROR(K12/L12,"") | N12: =IFERROR(K12-J12,"") | O12: =IFERROR(K12-L12,"") | P12: =IFERROR(Parâmetros!$B$36/M12,"") | Q12: =IFERROR(Parâmetros!$B$36-P12,"")
A13: R3 | B13: S12 | E13: =E12+C13 -> 0 | F13: =F12+D13 -> 0 | G13: =SUMIFS(Horas!$C:$C,Horas!$B:$B,$B13) -> 0 | H13: =H12+G13 -> 0 | I13: =IFERROR(F13/E13,"") | J13: =Parâmetros!$B$33*12 -> 47222.747 | K13: =IFERROR(I13*J13,"") | L13: =IFERROR(IF(H13=0,"",H13*Parâmetros!$B$28),"") | M13: =IFERROR(K13/L13,"") | N13: =IFERROR(K13-J13,"") | O13: =IFERROR(K13-L13,"") | P13: =IFERROR(Parâmetros!$B$36/M13,"") | Q13: =IFERROR(Parâmetros!$B$36-P13,"")
A14: R3 | B14: S13 | E14: =E13+C14 -> 0 | F14: =F13+D14 -> 0 | G14: =SUMIFS(Horas!$C:$C,Horas!$B:$B,$B14) -> 0 | H14: =H13+G14 -> 0 | I14: =IFERROR(F14/E14,"") | J14: =Parâmetros!$B$33*13 -> 51157.976 | K14: =IFERROR(I14*J14,"") | L14: =IFERROR(IF(H14=0,"",H14*Parâmetros!$B$28),"") | M14: =IFERROR(K14/L14,"") | N14: =IFERROR(K14-J14,"") | O14: =IFERROR(K14-L14,"") | P14: =IFERROR(Parâmetros!$B$36/M14,"") | Q14: =IFERROR(Parâmetros!$B$36-P14,"")
A15: R3 | B15: S14 | E15: =E14+C15 -> 0 | F15: =F14+D15 -> 0 | G15: =SUMIFS(Horas!$C:$C,Horas!$B:$B,$B15) -> 0 | H15: =H14+G15 -> 0 | I15: =IFERROR(F15/E15,"") | J15: =Parâmetros!$B$33*14 -> 55093.205 | K15: =IFERROR(I15*J15,"") | L15: =IFERROR(IF(H15=0,"",H15*Parâmetros!$B$28),"") | M15: =IFERROR(K15/L15,"") | N15: =IFERROR(K15-J15,"") | O15: =IFERROR(K15-L15,"") | P15: =IFERROR(Parâmetros!$B$36/M15,"") | Q15: =IFERROR(Parâmetros!$B$36-P15,"")
A16: R3 | B16: S15 | E16: =E15+C16 -> 0 | F16: =F15+D16 -> 0 | G16: =SUMIFS(Horas!$C:$C,Horas!$B:$B,$B16) -> 0 | H16: =H15+G16 -> 0 | I16: =IFERROR(F16/E16,"") | J16: =Parâmetros!$B$33*15 -> 59028.434 | K16: =IFERROR(I16*J16,"") | L16: =IFERROR(IF(H16=0,"",H16*Parâmetros!$B$28),"") | M16: =IFERROR(K16/L16,"") | N16: =IFERROR(K16-J16,"") | O16: =IFERROR(K16-L16,"") | P16: =IFERROR(Parâmetros!$B$36/M16,"") | Q16: =IFERROR(Parâmetros!$B$36-P16,"")
A18: Preencher os pontos planejados e concluídos de cada sprint pelo quadro do ZenHub e as horas de cada integrante na aba Horas.
A19: PV (R$) = custo semanal do projeto (baseline de 13) × sprints decorridas. EV (R$) = SPI × PV (R$). AC (R$) = horas reais acumuladas × custo-hora.
A20: Sem horas registradas o AC fica em branco e o CPI não é calculado. O AC nunca é substituído pelo custo planejado.
A21: Método: AgileEVM (Sulaiman, Barton e Blackburn, 2006). Os pontos planejados da release são congelados na planning; o escopo que entra depois aparece como ponto adicionado.
